Workbook

Sheet RAW DATA
A1: Metric | B1: Company | C1: FY2019 | D1: FY2020 | E1: FY2021 | F1: FY2022
A2: totalRevenue | B2: AMZN | C2: 125555 | D2: 108518 | E2: 113080 | F2: 110812
A3: totalRevenue | B3: NVDA | C3: 5003 | D3: 5661 | E3: 6507 | F3: 7103
A4: grossProfit | B4: AMZN | C4: 46271 | D4: 46115 | E4: 48904 | F4: 47882
A5: grossProfit | B5: NVDA | C5: 3156 | D5: 3629 | E5: 4215 | F5: 4631
A6: operatingIncome | B6: AMZN | C6: 6873 | D6: 8865 | E6: 7702 | F6: 4852
A7: operatingIncome | B7: NVDA | C7: 1508 | D7: 1956 | E7: 2444 | F7: 2671
A8: netIncome | B8: AMZN | C8: 7222 | D8: 8107 | E8: 7778 | F8: 3156
A9: netIncome | B9: NVDA | C9: 1457 | D9: 1912 | E9: 2374 | F9: 2464
A10: operatingCashFlow | B10: AMZN | C10: 30431 | D10: 4213 | E10: 12715 | F10: 7313
A11: operatingCashFlow | B11: NVDA | C11: 2067 | D11: 1874 | E11: 2682 | F11: 1519
A12: capitalExpenditures | B12: AMZN | C12: -14823 | D12: -12082 | E12: -14288 | F12: -15748
A13: capitalExpenditures | B13: NVDA | C13: -283 | D13: -298 | E13: -183 | F13: -222
... A15: depreciation | B15: NVDA | C15: 288 | D15: 281 | E15: 286 | F15: 298
A18: N:B | B18: All figures in USD Millions

Sheet Pro forma analysis (Combined en
A1: Project NOVA: Combined Entity Financial Summary
A2: All figures in USD Billions
A4: Metric | B4: FY2019 | C4: FY2020 | D4: FY2021 | E4: FY2022
A5: AMZN Revenue | B5: ='RAW DATA'!C2 -> 125555 | C5: ='RAW DATA'!D2 -> 108518 | D5: ='RAW DATA'!E2 -> 113080 | E5: ='RAW DATA'!F2 -> 110812
A6: NVDA Revenue | B6: ='RAW DATA'!C3 -> 5003 | C6: ='RAW DATA'!D3 -> 5661 | D6: ='RAW DATA'!E3 -> 6507 | E6: ='RAW DATA'!F3 -> 7103
A7: NOVA Combined Revenue | B7: =SUM(B5:B6) -> 130558 | C7: =SUM(C5:C6) -> 114179 | D7: =SUM(D5:D6) -> 119587 | E7: =SUM(E5:E6) -> 117915
A8: Synergy Adjustment | B8: 0 | C8: 0 | D8: 0 | E8: 0
A9: NOVA Adjusted Revenue | B9: =B7+B8 -> 130558 | C9: =C7+C8 -> 114179 | D9: =D7+D8 -> 119587 | E9: =E7+E8 -> 117915
A11: AMZN Gross Profit | B11: ='RAW DATA'!C4 -> 46271 | C11: ='RAW DATA'!D4 -> 46115 | D11: ='RAW DATA'!E4 -> 48904 | E11: ='RAW DATA'!F4 -> 47882
A12: NVDA Gross Profit | B12: ='RAW DATA'!C5 -> 3156 | C12: ='RAW DATA'!D5 -> 3629 | D12: ='RAW DATA'!E5 -> 4215 | E12: ='RAW DATA'!F5 -> 4631
A13: NOVA Combined Gross Profit | B13: =B11+B12 -> 49427 | C13: =C11+C12 -> 49744 | D13: =D11+D12 -> 53119 | E13: =E11+E12 -> 52513
A15: AMZN Operating Income | B15: ='RAW DATA'!C6 -> 6873 | C15: ='RAW DATA'!D6 -> 8865 | D15: ='RAW DATA'!E6 -> 7702 | E15: ='RAW DATA'!F6 -> 4852
A16: NVDA Operating Income | B16: ='RAW DATA'!C7 -> 1508 | C16: ='RAW DATA'!D7 -> 1956 | D16: ='RAW DATA'!E7 -> 2444 | E16: ='RAW DATA'!F7 -> 2671
A17: NOVA Combined Operating Income | B17: =B15+B16 -> 8381 | C17: =C15+C16 -> 10821 | D17: =D15+D16 -> 10146 | E17: =E15+E16 -> 7523
A19: AMZN Net Income | B19: ='RAW DATA'!C8 -> 7222 | C19: ='RAW DATA'!D8 -> 8107 | D19: ='RAW DATA'!E8 -> 7778 | E19: ='RAW DATA'!F8 -> 3156
A20: NVDA Net Income | B20: ='RAW DATA'!C9 -> 1457 | C20: ='RAW DATA'!D9 -> 1912 | D20: ='RAW DATA'!E9 -> 2374 | E20: ='RAW DATA'!F9 -> 2464
A21: NOVA Combined Net Income | B21: =B19+B20 -> 8679 | C21: =C19+C20 -> 10019 | D21: =D19+D20 -> 10152 | E21: =E19+E20 -> 5620
A23: AMZN Operating Cashflow | B23: ='RAW DATA'!C10 -> 30431 | C23: ='RAW DATA'!D10 -> 4213 | D23: ='RAW DATA'!E10 -> 12715 | E23: ='RAW DATA'!F10 -> 7313
A24: NVDA Operating Cashflow | B24: ='RAW DATA'!C11 -> 2067 | C24: ='RAW DATA'!D11 -> 1874 | D24: ='RAW DATA'!E11 -> 2682 | E24: ='RAW DATA'!F11 -> 1519
A25: NOVA Combined Operating Cashflow | B25: =B23+B24 -> 32498 | C25: =C23+C24 -> 6087 | D25: =D23+D24 -> 15397 | E25: =E23+E24 -> 8832
A27: AMZN CapEx | B27: ='RAW DATA'!C12 -> -14823 | C27: ='RAW DATA'!D12 -> -12082 | D27: ='RAW DATA'!E12 -> -14288 | E27: ='RAW DATA'!F12 -> -15748
A28: NVDA CapEx | B28: ='RAW DATA'!C13 -> -283 | C28: ='RAW DATA'!D13 -> -298 | D28: ='RAW DATA'!E13 -> -183 | E28: ='RAW DATA'!F13 -> -222
A29: NOVA Combined CapEx | B29: =B27+B28 -> -15106 | C29: =C27+C28 -> -12380 | D29: =D27+D28 -> -14471 | E29: =E27+E28 -> -15970
A31: NOVA Free Cash Flow (FCF) | B31: =B25+B29 -> 17392 | C31: =C25+C29 -> -6293 | D31: =D25+D29 -> 926 | E31: =E25+E29 -> -7138
A33: AMZN Depreciatiom | B33: ='RAW DATA'!C14 -> 7618 | C33: ='RAW DATA'!D14 -> 7508 | D33: ='RAW DATA'!E14 -> 8038 | E33: ='RAW DATA'!F14 -> 8948
A34: NVDA Depreciation | B34: ='RAW DATA'!C15 -> 288 | C34: ='RAW DATA'!D15 -> 281 | D34: ='RAW DATA'!E15 -> 286 | E34: ='RAW DATA'!F15 -> 298
A35: NOVA Combined Depreciation | B35: =B33+B34 -> 7906 | C35: =C33+C34 -> 7789 | D35: =D33+D34 -> 8324 | E35: =E33+E34 -> 9246

Sheet ASSUMPTIONS
A1: Project NOVA: Model Assumptions
A2: All rates and percentages in decimal form (e.g. 12% = 0.12)
A5: Assumptions | B5: Value | C5: Rationale
A7: Revenue Growth Rate: Year 1 | B7: 0.12 | C7: AI infrastructure demand accelerating. AWS growing double digits. NVIDIA chip demand surging with AI adoption.
A8: Revenue Growth Rate: Year 2 | B8: 0.14 | C8: Merger synergies beginning to materialise. NVIDIA chips selling directly through AWS platform. Combined R&D accelerating product development.
A9: Revenue Growth Rate: Year 3 | B9: 0.13 | C9: Synergies fully realised but growth beginning to normalise as combined entity matures. AI infrastructure market remains strong but early hyper-growth phase moderating.
A10: Revenue Growth Rate: Year 4 | B10: 0.1 | C10: Growth continuing to normalise as NOVA approaches scale ceiling. Market share gains slowing as competition intensifies in cloud and AI chip markets.
A11: Revenue Growth Rate: Year 5 | B11: 0.08 | C11: Approaching sustainable long term growth. Combined entity now one of largest companies globally. Maintaining 8% growth at this scale represents strong performance.
A13: FCF Margin: Year 1 | B13: 0.085 | C13: Conservative recovery from negative FCF position. CapEx beginning to normalise relative to revenue growth.
A14: FCF Margin: Year 2 | B14: 0.09 | C14: Synergy cost savings improving cash conversion.
A15: FCF Margin: Year 3 | B15: 0.095 | C15: Operating leverage building as revenue scales on existing infrastructure.
A16: FCF Margin: Year 4 | B16: 0.1 | C16: CapEx normalising. AWS and AI chip revenues highly scalable with minimal incremental cost.
A17: FCF Margin: Year 5 | B17: 0.105 | C17: Mature margin profile. Combined entity operating at full efficiency with diversified high margin revenue streams.
A19: WACC- Discount Rate | B19: 0.095 | C19: Blended WACC for combined entity. Derived from CAPM using 4.5% risk free rate, Amazon Beta 1.2, NVIDIA Beta 1.7, 5.5% market risk premium. Amazon dominates combined entity at 94% weight pulling blended WACC to 9.5%.
A21: Terminal Growth Rate | B21: 0.03 | C21: Above long term global GDP growth of 2.5%, justified by NOVA's dominance in AI infrastructure and cloud computing. Conservative relative to current sector growth rates.
... A29: Net Debt | B29: 32000 | C29: Estimated combined net debt position. Amazon total debt approximately $67B offset by $35B cash. NVIDIA minimal debt position. Combined net debt approximately $32B.

Sheet FCF_PROJECTION
A1: Project NOVA: 5 Year FCF Projection
A2: All figures in USD Millions
A4: Metric | B4: Year 1 | C4: Year 2 | D4: Year 3 | E4: Year 4 | F4: Year 5
B5: FY2023 | C5: FY2024 | D5: FY2025 | E5: FY2026 | F5: FY2027
A6: Base Revenue (FY2022) | B6: ='Pro forma analysis (Combined en'!E7 -> 117915
A7: Projected Revenue | B7: =B6*(1+ASSUMPTIONS!B7)*(1+ASSUMPTIONS!B25) -> 132064.8 | C7: =B7*(1+ASSUMPTIONS!B8)*(1+ASSUMPTIONS!B26) -> 158081.57 | D7: =C7*(1+ASSUMPTIONS!B9)*(1+ASSUMPTIONS!B27) -> 192922.74 | E7: =D7*(1+ASSUMPTIONS!B10)*(1+ASSUMPTIONS!B27) -> 229192.22 | F7: =E7*(1+ASSUMPTIONS!B11)*(1+ASSUMPTIONS!B27) -> 267329.8
A8: Free Cash Flow | B8: =B7*ASSUMPTIONS!B13 -> 11225.508 | C8: =C7*ASSUMPTIONS!B14 -> 14227.341 | D8: =D7*ASSUMPTIONS!B15 -> 18327.661 | E8: =E7*ASSUMPTIONS!B16 -> 22919.222 | F8: =F7*ASSUMPTIONS!B17 -> 28069.629
A9: Discount Factor | B9: =1/(1+ASSUMPTIONS!B19)^1 -> 0.91324201 | C9: =1/(1+ASSUMPTIONS!B19)^2 -> 0.83401097 | D9: =1/(1+ASSUMPTIONS!B19)^3 -> 0.76165385 | E9: =1/(1+ASSUMPTIONS!B19)^4 -> 0.69557429 | F9: =1/(1+ASSUMPTIONS!B19)^5 -> 0.63522767
A10: Present Value of FCF | B10: =B8*B9 -> 10251.605 | C10: =C8*C9 -> 11865.758 | D10: =D8*D9 -> 13959.333 | E10: =E8*E9 -> 15942.022 | F10: =F8*F9 -> 17830.605
A11: Sum of PV (FCFs) | B11: =SUM(B10:F10) -> 69849.324
A12: Terminal Value | B12: =F8*(1+ASSUMPTIONS!B21)/(ASSUMPTIONS!B19-ASSUMPTIONS!B21) -> 444795.67
A13: PV of Terminal Value | B13: =B12*F9 -> 282546.51
A14: Enterprise Value | B14: =B11+B13 -> 352395.84
A15: Less Net Debt | B15: =ASSUMPTIONS!B29 -> 32000
A16: Equity Value | B16: =B14-B15 -> 320395.84

Sheet VALUATION_SUMMARY
A1: Project NOVA: Valuation Summary
A2: Hypothetical Merger: Amazon (AMZN) + NVIDIA (NVDA)
A3: All figures in USD Millions
A5: DEAL OVERVIEW
A6: Combined Entity | B6: Amazon (AMZN) + NVIDIA (NVDA)
A7: Base Year | B7: FY2022
A8: Forecast Period | B8: FY2023-FY2027
A10: KEY ASSUMPTIONS
A11: WACC | B11: =ASSUMPTIONS!B19 -> 0.095
A12: TERNINAL GROWTH RATE | B12: =ASSUMPTIONS!B21 -> 0.03
A13: TAX RATE | B13: =ASSUMPTIONS!B23 -> 0.12
A14: Year 1 Revenue Growth | B14: =ASSUMPTIONS!B7 -> 0.12
A15: Year 5 Revenue Growth | B15: =ASSUMPTIONS!B11 -> 0.08
A16: Peak Synergy Premium | B16: =ASSUMPTIONS!B27 -> 0.08
A18: VALUATION OUTPUTS
A19: Base Revenue (FY2022) | B19: =FCF_PROJECTION!B6 -> 117915
A20: Year 5 Projected Revenue | B20: =FCF_PROJECTION!F7 -> 267329.8
A21: Year 1 Free Cash Flow | B21: =FCF_PROJECTION!B8 -> 11225.508
A22: Year 5 Free Cash Flow | B22: =FCF_PROJECTION!F8 -> 28069.629
A23: Sum of PV of FCFs | B23: =FCF_PROJECTION!B11 -> 69849.324
A24: PV of Terminal Value | B24: =FCF_PROJECTION!B13 -> 282546.51
A25: Enterprise Value | B25: =FCF_PROJECTION!B14 -> 352395.84
A26: Less Net Debt | B26: =FCF_PROJECTION!B15 -> 32000
A27: Equity Value | B27: =FCF_PROJECTION!B16 -> 320395.84
A29: KEY INSIGHTS
A30: Revenue Growth | B30: NOVA grows from $118B to $267B over 5 years, a 127% increase driven by AI infrastructure demand and merger synergies
A31: FCF Transformation | B31: FCF transforms from -$7.1B in FY2022 to +$28.1B in Year 5 as heavy CapEx investment phase concludes
A32: Value Composition | B32: Terminal Value represents 80% of Enterprise Value, reflecting NOVA's long duration cash generation profile
A33: Synergy Impact | B33: Synergy premium adds approximately $35B in cumulative revenue over the forecast period
A35: Model built by Opene-Terry Josephine | Project NOVA DCF Valuation | Data Source: S&P 500 Financial Statements

Sheet SENSITIVITY_ANALYSIS
A1: Project NOVA — Sensitivity Analysis
A2: Base Case: Enterprise Value $352,396M | Equity Value $320,396M
A3: All figures in USD Millions
A5: TABLE 1: Enterprise Value Sensitivity
A6: WACC vs Terminal Growth Rate (USD Millions) | J6: =$A8 -> 0.075
A7: WACC / TGR | B7: 0.015 | C7: 0.02 | D7: 0.025 | E7: 0.03 | F7: 0.035 | G7: 0.04 | H7: 0.045 | J7: =B$7 -> 0.015
A8: 0.075 | B8: =(INDIRECT("FCF_PROJECTION!B8")/(1+$A8)^1)+(INDIRECT("FCF_PROJECTION!C8")/(1+$A8)^2)+(INDIRECT("FCF_PROJECTION!D8")/(1+$A8)^3)+(INDIRECT("FCF_PROJECTION!E8")/(1+$A8)^4)+(INDIRECT("FCF_PROJECTION!F8")/(1+$A8)^5)+((INDIRECT("FCF_PROJECTION!F8")*(1+B$7)/($A8-B$7))/(1+$A8)^5) -> 404977.91 | C8: =(INDIRECT("FCF_PROJECTION!B8")/(1+$A8)^1)+(INDIRECT("FCF_PROJECTION!C8")/(1+$A8)^2)+(INDIRECT("FCF_PROJECTION!D8")/(1+$A8)^3)+(INDIRECT("FCF_PROJECTION!E8")/(1+$A8)^4)+(INDIRECT("FCF_PROJECTION!F8")/(1+$A8)^5)+((INDIRECT("FCF_PROJECTION!F8")*(1+C$7)/($A8-C$7))/(1+$A8)^5) -> 436824.2 | D8: =(INDIRECT("FCF_PROJECTION!B8")/(1+$A8)^1)+(INDIRECT("FCF_PROJECTION!C8")/(1+$A8)^2)+(INDIRECT("FCF_PROJECTION!D8")/(1+$A8)^3)+(INDIRECT("FCF_PROJECTION!E8")/(1+$A8)^4)+(INDIRECT("FCF_PROJECTION!F8")/(1+$A8)^5)+((INDIRECT("FCF_PROJECTION!F8")*(1+D$7)/($A8-D$7))/(1+$A8)^5) -> 475039.75 | E8: =(INDIRECT("FCF_PROJECTION!B8")/(1+$A8)^1)+(INDIRECT("FCF_PROJECTION!C8")/(1+$A8)^2)+(INDIRECT("FCF_PROJECTION!D8")/(1+$A8)^3)+(INDIRECT("FCF_PROJECTION!E8")/(1+$A8)^4)+(INDIRECT("FCF_PROJECTION!F8")/(1+$A8)^5)+((INDIRECT("FCF_PROJECTION!F8")*(1+E$7)/($A8-E$7))/(1+$A8)^5) -> 521747.65 | F8: =(INDIRECT("FCF_PROJECTION!B8")/(1+$A8)^1)+(INDIRECT("FCF_PROJECTION!C8")/(1+$A8)^2)+(INDIRECT("FCF_PROJECTION!D8")/(1+$A8)^3)+(INDIRECT("FCF_PROJECTION!E8")/(1+$A8)^4)+(INDIRECT("FCF_PROJECTION!F8")/(1+$A8)^5)+((INDIRECT("FCF_PROJECTION!F8")*(1+F$7)/($A8-F$7))/(1+$A8)^5) -> 580132.52 | G8: =(INDIRECT("FCF_PROJECTION!B8")/(1+$A8)^1)+(INDIRECT("FCF_PROJECTION!C8")/(1+$A8)^2)+(INDIRECT("FCF_PROJECTION!D8")/(1+$A8)^3)+(INDIRECT("FCF_PROJECTION!E8")/(1+$A8)^4)+(INDIRECT("FCF_PROJECTION!F8")/(1+$A8)^5)+((INDIRECT("FCF_PROJECTION!F8")*(1+G$7)/($A8-G$7))/(1+$A8)^5) -> 655198.78 | H8: =(INDIRECT("FCF_PROJECTION!B8")/(1+$A8)^1)+(INDIRECT("FCF_PROJECTION!C8")/(1+$A8)^2)+(INDIRECT("FCF_PROJECTION!D8")/(1+$A8)^3)+(INDIRECT("FCF_PROJECTION!E8")/(1+$A8)^4)+(INDIRECT("FCF_PROJECTION!F8")/(1+$A8)^5)+((INDIRECT("FCF_PROJECTION!F8")*(1+H$7)/($A8-H$7))/(1+$A8)^5) -> 755287.13 | J8: =FCF_PROJECTION!B8 -> 11225.508
A9: 0.08 | B9: =(INDIRECT("FCF_PROJECTION!B8")/(1+$A9)^1)+(INDIRECT("FCF_PROJECTION!C8")/(1+$A9)^2)+(INDIRECT("FCF_PROJECTION!D8")/(1+$A9)^3)+(INDIRECT("FCF_PROJECTION!E8")/(1+$A9)^4)+(INDIRECT("FCF_PROJECTION!F8")/(1+$A9)^5)+((INDIRECT("FCF_PROJECTION!F8")*(1+B$7)/($A9-B$7))/(1+$A9)^5) -> 371402.66 | C9: =(INDIRECT("FCF_PROJECTION!B8")/(1+$A9)^1)+(INDIRECT("FCF_PROJECTION!C8")/(1+$A9)^2)+(INDIRECT("FCF_PROJECTION!D8")/(1+$A9)^3)+(INDIRECT("FCF_PROJECTION!E8")/(1+$A9)^4)+(INDIRECT("FCF_PROJECTION!F8")/(1+$A9)^5)+((INDIRECT("FCF_PROJECTION!F8")*(1+C$7)/($A9-C$7))/(1+$A9)^5) -> 397853.97 | D9: =(INDIRECT("FCF_PROJECTION!B8")/(1+$A9)^1)+(INDIRECT("FCF_PROJECTION!C8")/(1+$A9)^2)+(INDIRECT("FCF_PROJECTION!D8")/(1+$A9)^3)+(INDIRECT("FCF_PROJECTION!E8")/(1+$A9)^4)+(INDIRECT("FCF_PROJECTION!F8")/(1+$A9)^5)+((INDIRECT("FCF_PROJECTION!F8")*(1+D$7)/($A9-D$7))/(1+$A9)^5) -> 429114.6 | E9: =(INDIRECT("FCF_PROJECTION!B8")/(1+$A9)^1)+(INDIRECT("FCF_PROJECTION!C8")/(1+$A9)^2)+(INDIRECT("FCF_PROJECTION!D8")/(1+$A9)^3)+(INDIRECT("FCF_PROJECTION!E8")/(1+$A9)^4)+(INDIRECT("FCF_PROJECTION!F8")/(1+$A9)^5)+((INDIRECT("FCF_PROJECTION!F8")*(1+E$7)/($A9-E$7))/(1+$A9)^5) -> 466627.35 | F9: =(INDIRECT("FCF_PROJECTION!B8")/(1+$A9)^1)+(INDIRECT("FCF_PROJECTION!C8")/(1+$A9)^2)+(INDIRECT("FCF_PROJECTION!D8")/(1+$A9)^3)+(INDIRECT("FCF_PROJECTION!E8")/(1+$A9)^4)+(INDIRECT("FCF_PROJECTION!F8")/(1+$A9)^5)+((INDIRECT("FCF_PROJECTION!F8")*(1+F$7)/($A9-F$7))/(1+$A9)^5) -> 512476.27 | G9: =(INDIRECT("FCF_PROJECTION!B8")/(1+$A9)^1)+(INDIRECT("FCF_PROJECTION!C8")/(1+$A9)^2)+(INDIRECT("FCF_PROJECTION!D8")/(1+$A9)^3)+(INDIRECT("FCF_PROJECTION!E8")/(1+$A9)^4)+(INDIRECT("FCF_PROJECTION!F8")/(1+$A9)^5)+((INDIRECT("FCF_PROJECTION!F8")*(1+G$7)/($A9-G$7))/(1+$A9)^5) -> 569787.43 | H9: =(INDIRECT("FCF_PROJECTION!B8")/(1+$A9)^1)+(INDIRECT("FCF_PROJECTION!C8")/(1+$A9)^2)+(INDIRECT("FCF_PROJECTION!D8")/(1+$A9)^3)+(INDIRECT("FCF_PROJECTION!E8")/(1+$A9)^4)+(INDIRECT("FCF_PROJECTION!F8")/(1+$A9)^5)+((INDIRECT("FCF_PROJECTION!F8")*(1+H$7)/($A9-H$7))/(1+$A9)^5) -> 643473.2 | J9: =(FCF_PROJECTION!F8*(1+B$7)/($A8-B$7))/(1+$A8)^5 -> 330757.08
A10: 0.085 | B10: =(INDIRECT("FCF_PROJECTION!B8")/(1+$A10)^1)+(INDIRECT("FCF_PROJECTION!C8")/(1+$A10)^2)+(INDIRECT("FCF_PROJECTION!D8")/(1+$A10)^3)+(INDIRECT("FCF_PROJECTION!E8")/(1+$A10)^4)+(INDIRECT("FCF_PROJECTION!F8")/(1+$A10)^5)+((INDIRECT("FCF_PROJECTION!F8")*(1+B$7)/($A10-B$7))/(1+$A10)^5) -> 342665.84 | C10: =(INDIRECT("FCF_PROJECTION!B8")/(1+$A10)^1)+(INDIRECT("FCF_PROJECTION!C8")/(1+$A10)^2)+(INDIRECT("FCF_PROJECTION!D8")/(1+$A10)^3)+(INDIRECT("FCF_PROJECTION!E8")/(1+$A10)^4)+(INDIRECT("FCF_PROJECTION!F8")/(1+$A10)^5)+((INDIRECT("FCF_PROJECTION!F8")*(1+C$7)/($A10-C$7))/(1+$A10)^5) -> 364923.34 | D10: =(INDIRECT("FCF_PROJECTION!B8")/(1+$A10)^1)+(INDIRECT("FCF_PROJECTION!C8")/(1+$A10)^2)+(INDIRECT("FCF_PROJECTION!D8")/(1+$A10)^3)+(INDIRECT("FCF_PROJECTION!E8")/(1+$A10)^4)+(INDIRECT("FCF_PROJECTION!F8")/(1+$A10)^5)+((INDIRECT("FCF_PROJECTION!F8")*(1+D$7)/($A10-D$7))/(1+$A10)^5) -> 390890.42 | E10: =(INDIRECT("FCF_PROJECTION!B8")/(1+$A10)^1)+(INDIRECT("FCF_PROJECTION!C8")/(1+$A10)^2)+(INDIRECT("FCF_PROJECTION!D8")/(1+$A10)^3)+(INDIRECT("FCF_PROJECTION!E8")/(1+$A10)^4)+(INDIRECT("FCF_PROJECTION!F8")/(1+$A10)^5)+((INDIRECT("FCF_PROJECTION!F8")*(1+E$7)/($A10-E$7))/(1+$A10)^5) -> 421578.79 | F10: =(INDIRECT("FCF_PROJECTION!B8")/(1+$A10)^1)+(INDIRECT("FCF_PROJECTION!C8")/(1+$A10)^2)+(INDIRECT("FCF_PROJECTION!D8")/(1+$A10)^3)+(INDIRECT("FCF_PROJECTION!E8")/(1+$A10)^4)+(INDIRECT("FCF_PROJECTION!F8")/(1+$A10)^5)+((INDIRECT("FCF_PROJECTION!F8")*(1+F$7)/($A10-F$7))/(1+$A10)^5) -> 458404.83 | G10: =(INDIRECT("FCF_PROJECTION!B8")/(1+$A10)^1)+(INDIRECT("FCF_PROJECTION!C8")/(1+$A10)^2)+(INDIRECT("FCF_PROJECTION!D8")/(1+$A10)^3)+(INDIRECT("FCF_PROJECTION!E8")/(1+$A10)^4)+(INDIRECT("FCF_PROJECTION!F8")/(1+$A10)^5)+((INDIRECT("FCF_PROJECTION!F8")*(1+G$7)/($A10-G$7))/(1+$A10)^5) -> 503414.44 | H10: =(INDIRECT("FCF_PROJECTION!B8")/(1+$A10)^1)+(INDIRECT("FCF_PROJECTION!C8")/(1+$A10)^2)+(INDIRECT("FCF_PROJECTION!D8")/(1+$A10)^3)+(INDIRECT("FCF_PROJECTION!E8")/(1+$A10)^4)+(INDIRECT("FCF_PROJECTION!F8")/(1+$A10)^5)+((INDIRECT("FCF_PROJECTION!F8")*(1+H$7)/($A10-H$7))/(1+$A10)^5) -> 559676.44 | J10: =(FCF_PROJECTION!B8/(1+$A8)^1)+(FCF_PROJECTION!C8/(1+$A8)^2)+(FCF_PROJECTION!D8/(1+$A8)^3)+(FCF_PROJECTION!E8/(1+$A8)^4)+(FCF_PROJECTION!F8/(1+$A8)^5) -> 74220.827
A11: 0.09 | B11: =(INDIRECT("FCF_PROJECTION!B8")/(1+$A11)^1)+(INDIRECT("FCF_PROJECTION!C8")/(1+$A11)^2)+(INDIRECT("FCF_PROJECTION!D8")/(1+$A11)^3)+(INDIRECT("FCF_PROJECTION!E8")/(1+$A11)^4)+(INDIRECT("FCF_PROJECTION!F8")/(1+$A11)^5)+((INDIRECT("FCF_PROJECTION!F8")*(1+B$7)/($A11-B$7))/(1+$A11)^5) -> 317798.81 | C11: =(INDIRECT("FCF_PROJECTION!B8")/(1+$A11)^1)+(INDIRECT("FCF_PROJECTION!C8")/(1+$A11)^2)+(INDIRECT("FCF_PROJECTION!D8")/(1+$A11)^3)+(INDIRECT("FCF_PROJECTION!E8")/(1+$A11)^4)+(INDIRECT("FCF_PROJECTION!F8")/(1+$A11)^5)+((INDIRECT("FCF_PROJECTION!F8")*(1+C$7)/($A11-C$7))/(1+$A11)^5) -> 336737.13 | D11: =(INDIRECT("FCF_PROJECTION!B8")/(1+$A11)^1)+(INDIRECT("FCF_PROJECTION!C8")/(1+$A11)^2)+(INDIRECT("FCF_PROJECTION!D8")/(1+$A11)^3)+(INDIRECT("FCF_PROJECTION!E8")/(1+$A11)^4)+(INDIRECT("FCF_PROJECTION!F8")/(1+$A11)^5)+((INDIRECT("FCF_PROJECTION!F8")*(1+D$7)/($A11-D$7))/(1+$A11)^5) -> 358589.03 | E11: =(INDIRECT("FCF_PROJECTION!B8")/(1+$A11)^1)+(INDIRECT("FCF_PROJECTION!C8")/(1+$A11)^2)+(INDIRECT("FCF_PROJECTION!D8")/(1+$A11)^3)+(INDIRECT("FCF_PROJECTION!E8")/(1+$A11)^4)+(INDIRECT("FCF_PROJECTION!F8")/(1+$A11)^5)+((INDIRECT("FCF_PROJECTION!F8")*(1+E$7)/($A11-E$7))/(1+$A11)^5) -> 384082.92 | F11: =(INDIRECT("FCF_PROJECTION!B8")/(1+$A11)^1)+(INDIRECT("FCF_PROJECTION!C8")/(1+$A11)^2)+(INDIRECT("FCF_PROJECTION!D8")/(1+$A11)^3)+(INDIRECT("FCF_PROJECTION!E8")/(1+$A11)^4)+(INDIRECT("FCF_PROJECTION!F8")/(1+$A11)^5)+((INDIRECT("FCF_PROJECTION!F8")*(1+F$7)/($A11-F$7))/(1+$A11)^5) -> 414212.06 | G11: =(INDIRECT("FCF_PROJECTION!B8")/(1+$A11)^1)+(INDIRECT("FCF_PROJECTION!C8")/(1+$A11)^2)+(INDIRECT("FCF_PROJECTION!D8")/(1+$A11)^3)+(INDIRECT("FCF_PROJECTION!E8")/(1+$A11)^4)+(INDIRECT("FCF_PROJECTION!F8")/(1+$A11)^5)+((INDIRECT("FCF_PROJECTION!F8")*(1+G$7)/($A11-G$7))/(1+$A11)^5) -> 450367.03 | H11: =(INDIRECT("FCF_PROJECTION!B8")/(1+$A11)^1)+(INDIRECT("FCF_PROJECTION!C8")/(1+$A11)^2)+(INDIRECT("FCF_PROJECTION!D8")/(1+$A11)^3)+(INDIRECT("FCF_PROJECTION!E8")/(1+$A11)^4)+(INDIRECT("FCF_PROJECTION!F8")/(1+$A11)^5)+((INDIRECT("FCF_PROJECTION!F8")*(1+H$7)/($A11-H$7))/(1+$A11)^5) -> 494556.44 | J11: =J9+J10 -> 404977.91
A12: 0.095 | B12: =(INDIRECT("FCF_PROJECTION!B8")/(1+$A12)^1)+(INDIRECT("FCF_PROJECTION!C8")/(1+$A12)^2)+(INDIRECT("FCF_PROJECTION!D8")/(1+$A12)^3)+(INDIRECT("FCF_PROJECTION!E8")/(1+$A12)^4)+(INDIRECT("FCF_PROJECTION!F8")/(1+$A12)^5)+((INDIRECT("FCF_PROJECTION!F8")*(1+B$7)/($A12-B$7))/(1+$A12)^5) -> 296075.13 | C12: =(INDIRECT("FCF_PROJECTION!B8")/(1+$A12)^1)+(INDIRECT("FCF_PROJECTION!C8")/(1+$A12)^2)+(INDIRECT("FCF_PROJECTION!D8")/(1+$A12)^3)+(INDIRECT("FCF_PROJECTION!E8")/(1+$A12)^4)+(INDIRECT("FCF_PROJECTION!F8")/(1+$A12)^5)+((INDIRECT("FCF_PROJECTION!F8")*(1+C$7)/($A12-C$7))/(1+$A12)^5) -> 312345.55 | D12: =(INDIRECT("FCF_PROJECTION!B8")/(1+$A12)^1)+(INDIRECT("FCF_PROJECTION!C8")/(1+$A12)^2)+(INDIRECT("FCF_PROJECTION!D8")/(1+$A12)^3)+(INDIRECT("FCF_PROJECTION!E8")/(1+$A12)^4)+(INDIRECT("FCF_PROJECTION!F8")/(1+$A12)^5)+((INDIRECT("FCF_PROJECTION!F8")*(1+D$7)/($A12-D$7))/(1+$A12)^5) -> 330940.33 | E12: =(INDIRECT("FCF_PROJECTION!B8")/(1+$A12)^1)+(INDIRECT("FCF_PROJECTION!C8")/(1+$A12)^2)+(INDIRECT("FCF_PROJECTION!D8")/(1+$A12)^3)+(INDIRECT("FCF_PROJECTION!E8")/(1+$A12)^4)+(INDIRECT("FCF_PROJECTION!F8")/(1+$A12)^5)+((INDIRECT("FCF_PROJECTION!F8")*(1+E$7)/($A12-E$7))/(1+$A12)^5) -> 352395.84 | F12: =(INDIRECT("FCF_PROJECTION!B8")/(1+$A12)^1)+(INDIRECT("FCF_PROJECTION!C8")/(1+$A12)^2)+(INDIRECT("FCF_PROJECTION!D8")/(1+$A12)^3)+(INDIRECT("FCF_PROJECTION!E8")/(1+$A12)^4)+(INDIRECT("FCF_PROJECTION!F8")/(1+$A12)^5)+((INDIRECT("FCF_PROJECTION!F8")*(1+F$7)/($A12-F$7))/(1+$A12)^5) -> 377427.26 | G12: =(INDIRECT("FCF_PROJECTION!B8")/(1+$A12)^1)+(INDIRECT("FCF_PROJECTION!C8")/(1+$A12)^2)+(INDIRECT("FCF_PROJECTION!D8")/(1+$A12)^3)+(INDIRECT("FCF_PROJECTION!E8")/(1+$A12)^4)+(INDIRECT("FCF_PROJECTION!F8")/(1+$A12)^5)+((INDIRECT("FCF_PROJECTION!F8")*(1+G$7)/($A12-G$7))/(1+$A12)^5) -> 407009.86 | H12: =(INDIRECT("FCF_PROJECTION!B8")/(1+$A12)^1)+(INDIRECT("FCF_PROJECTION!C8")/(1+$A12)^2)+(INDIRECT("FCF_PROJECTION!D8")/(1+$A12)^3)+(INDIRECT("FCF_PROJECTION!E8")/(1+$A12)^4)+(INDIRECT("FCF_PROJECTION!F8")/(1+$A12)^5)+((INDIRECT("FCF_PROJECTION!F8")*(1+H$7)/($A12-H$7))/(1+$A12)^5) -> 442508.97
A13: 0.1 | B13: =(INDIRECT("FCF_PROJECTION!B8")/(1+$A13)^1)+(INDIRECT("FCF_PROJECTION!C8")/(1+$A13)^2)+(INDIRECT("FCF_PROJECTION!D8")/(1+$A13)^3)+(INDIRECT("FCF_PROJECTION!E8")/(1+$A13)^4)+(INDIRECT("FCF_PROJECTION!F8")/(1+$A13)^5)+((INDIRECT("FCF_PROJECTION!F8")*(1+B$7)/($A13-B$7))/(1+$A13)^5) -> 276939.29 | C13: =(INDIRECT("FCF_PROJECTION!B8")/(1+$A13)^1)+(INDIRECT("FCF_PROJECTION!C8")/(1+$A13)^2)+(INDIRECT("FCF_PROJECTION!D8")/(1+$A13)^3)+(INDIRECT("FCF_PROJECTION!E8")/(1+$A13)^4)+(INDIRECT("FCF_PROJECTION!F8")/(1+$A13)^5)+((INDIRECT("FCF_PROJECTION!F8")*(1+C$7)/($A13-C$7))/(1+$A13)^5) -> 291036.3 | D13: =(INDIRECT("FCF_PROJECTION!B8")/(1+$A13)^1)+(INDIRECT("FCF_PROJECTION!C8")/(1+$A13)^2)+(INDIRECT("FCF_PROJECTION!D8")/(1+$A13)^3)+(INDIRECT("FCF_PROJECTION!E8")/(1+$A13)^4)+(INDIRECT("FCF_PROJECTION!F8")/(1+$A13)^5)+((INDIRECT("FCF_PROJECTION!F8")*(1+D$7)/($A13-D$7))/(1+$A13)^5) -> 307012.91 | E13: =(INDIRECT("FCF_PROJECTION!B8")/(1+$A13)^1)+(INDIRECT("FCF_PROJECTION!C8")/(1+$A13)^2)+(INDIRECT("FCF_PROJECTION!D8")/(1+$A13)^3)+(INDIRECT("FCF_PROJECTION!E8")/(1+$A13)^4)+(INDIRECT("FCF_PROJECTION!F8")/(1+$A13)^5)+((INDIRECT("FCF_PROJECTION!F8")*(1+E$7)/($A13-E$7))/(1+$A13)^5) -> 325271.9 | F13: =(INDIRECT("FCF_PROJECTION!B8")/(1+$A13)^1)+(INDIRECT("FCF_PROJECTION!C8")/(1+$A13)^2)+(INDIRECT("FCF_PROJECTION!D8")/(1+$A13)^3)+(INDIRECT("FCF_PROJECTION!E8")/(1+$A13)^4)+(INDIRECT("FCF_PROJECTION!F8")/(1+$A13)^5)+((INDIRECT("FCF_PROJECTION!F8")*(1+F$7)/($A13-F$7))/(1+$A13)^5) -> 346339.96 | G13: =(INDIRECT("FCF_PROJECTION!B8")/(1+$A13)^1)+(INDIRECT("FCF_PROJECTION!C8")/(1+$A13)^2)+(INDIRECT("FCF_PROJECTION!D8")/(1+$A13)^3)+(INDIRECT("FCF_PROJECTION!E8")/(1+$A13)^4)+(INDIRECT("FCF_PROJECTION!F8")/(1+$A13)^5)+((INDIRECT("FCF_PROJECTION!F8")*(1+G$7)/($A13-G$7))/(1+$A13)^5) -> 370919.36 | H13: =(INDIRECT("FCF_PROJECTION!B8")/(1+$A13)^1)+(INDIRECT("FCF_PROJECTION!C8")/(1+$A13)^2)+(INDIRECT("FCF_PROJECTION!D8")/(1+$A13)^3)+(INDIRECT("FCF_PROJECTION!E8")/(1+$A13)^4)+(INDIRECT("FCF_PROJECTION!F8")/(1+$A13)^5)+((INDIRECT("FCF_PROJECTION!F8")*(1+H$7)/($A13-H$7))/(1+$A13)^5) -> 399967.75
A14: 0.105 | B14: =(INDIRECT("FCF_PROJECTION!B8")/(1+$A14)^1)+(INDIRECT("FCF_PROJECTION!C8")/(1+$A14)^2)+(INDIRECT("FCF_PROJECTION!D8")/(1+$A14)^3)+(INDIRECT("FCF_PROJECTION!E8")/(1+$A14)^4)+(INDIRECT("FCF_PROJECTION!F8")/(1+$A14)^5)+((INDIRECT("FCF_PROJECTION!F8")*(1+B$7)/($A14-B$7))/(1+$A14)^5) -> 259959.28 | C14: =(INDIRECT("FCF_PROJECTION!B8")/(1+$A14)^1)+(INDIRECT("FCF_PROJECTION!C8")/(1+$A14)^2)+(INDIRECT("FCF_PROJECTION!D8")/(1+$A14)^3)+(INDIRECT("FCF_PROJECTION!E8")/(1+$A14)^4)+(INDIRECT("FCF_PROJECTION!F8")/(1+$A14)^5)+((INDIRECT("FCF_PROJECTION!F8")*(1+C$7)/($A14-C$7))/(1+$A14)^5) -> 272264.69 | D14: =(INDIRECT("FCF_PROJECTION!B8")/(1+$A14)^1)+(INDIRECT("FCF_PROJECTION!C8")/(1+$A14)^2)+(INDIRECT("FCF_PROJECTION!D8")/(1+$A14)^3)+(INDIRECT("FCF_PROJECTION!E8")/(1+$A14)^4)+(INDIRECT("FCF_PROJECTION!F8")/(1+$A14)^5)+((INDIRECT("FCF_PROJECTION!F8")*(1+D$7)/($A14-D$7))/(1+$A14)^5) -> 286108.28 | E14: =(INDIRECT("FCF_PROJECTION!B8")/(1+$A14)^1)+(INDIRECT("FCF_PROJECTION!C8")/(1+$A14)^2)+(INDIRECT("FCF_PROJECTION!D8")/(1+$A14)^3)+(INDIRECT("FCF_PROJECTION!E8")/(1+$A14)^4)+(INDIRECT("FCF_PROJECTION!F8")/(1+$A14)^5)+((INDIRECT("FCF_PROJECTION!F8")*(1+E$7)/($A14-E$7))/(1+$A14)^5) -> 301797.67 | F14: =(INDIRECT("FCF_PROJECTION!B8")/(1+$A14)^1)+(INDIRECT("FCF_PROJECTION!C8")/(1+$A14)^2)+(INDIRECT("FCF_PROJECTION!D8")/(1+$A14)^3)+(INDIRECT("FCF_PROJECTION!E8")/(1+$A14)^4)+(INDIRECT("FCF_PROJECTION!F8")/(1+$A14)^5)+((INDIRECT("FCF_PROJECTION!F8")*(1+F$7)/($A14-F$7))/(1+$A14)^5) -> 319728.42 | G14: =(INDIRECT("FCF_PROJECTION!B8")/(1+$A14)^1)+(INDIRECT("FCF_PROJECTION!C8")/(1+$A14)^2)+(INDIRECT("FCF_PROJECTION!D8")/(1+$A14)^3)+(INDIRECT("FCF_PROJECTION!E8")/(1+$A14)^4)+(INDIRECT("FCF_PROJECTION!F8")/(1+$A14)^5)+((INDIRECT("FCF_PROJECTION!F8")*(1+G$7)/($A14-G$7))/(1+$A14)^5) -> 340417.73 | H14: =(INDIRECT("FCF_PROJECTION!B8")/(1+$A14)^1)+(INDIRECT("FCF_PROJECTION!C8")/(1+$A14)^2)+(INDIRECT("FCF_PROJECTION!D8")/(1+$A14)^3)+(INDIRECT("FCF_PROJECTION!E8")/(1+$A14)^4)+(INDIRECT("FCF_PROJECTION!F8")/(1+$A14)^5)+((INDIRECT("FCF_PROJECTION!F8")*(1+H$7)/($A14-H$7))/(1+$A14)^5) -> 364555.27
A15: 0.11 | B15: =(INDIRECT("FCF_PROJECTION!B8")/(1+$A15)^1)+(INDIRECT("FCF_PROJECTION!C8")/(1+$A15)^2)+(INDIRECT("FCF_PROJECTION!D8")/(1+$A15)^3)+(INDIRECT("FCF_PROJECTION!E8")/(1+$A15)^4)+(INDIRECT("FCF_PROJECTION!F8")/(1+$A15)^5)+((INDIRECT("FCF_PROJECTION!F8")*(1+B$7)/($A15-B$7))/(1+$A15)^5) -> 244794.03 | C15: =(INDIRECT("FCF_PROJECTION!B8")/(1+$A15)^1)+(INDIRECT("FCF_PROJECTION!C8")/(1+$A15)^2)+(INDIRECT("FCF_PROJECTION!D8")/(1+$A15)^3)+(INDIRECT("FCF_PROJECTION!E8")/(1+$A15)^4)+(INDIRECT("FCF_PROJECTION!F8")/(1+$A15)^5)+((INDIRECT("FCF_PROJECTION!F8")*(1+C$7)/($A15-C$7))/(1+$A15)^5) -> 255607.09 | D15: =(INDIRECT("FCF_PROJECTION!B8")/(1+$A15)^1)+(INDIRECT("FCF_PROJECTION!C8")/(1+$A15)^2)+(INDIRECT("FCF_PROJECTION!D8")/(1+$A15)^3)+(INDIRECT("FCF_PROJECTION!E8")/(1+$A15)^4)+(INDIRECT("FCF_PROJECTION!F8")/(1+$A15)^5)+((INDIRECT("FCF_PROJECTION!F8")*(1+D$7)/($A15-D$7))/(1+$A15)^5) -> 267692.27 | E15: =(INDIRECT("FCF_PROJECTION!B8")/(1+$A15)^1)+(INDIRECT("FCF_PROJECTION!C8")/(1+$A15)^2)+(INDIRECT("FCF_PROJECTION!D8")/(1+$A15)^3)+(INDIRECT("FCF_PROJECTION!E8")/(1+$A15)^4)+(INDIRECT("FCF_PROJECTION!F8")/(1+$A15)^5)+((INDIRECT("FCF_PROJECTION!F8")*(1+E$7)/($A15-E$7))/(1+$A15)^5) -> 281288.11 | F15: =(INDIRECT("FCF_PROJECTION!B8")/(1+$A15)^1)+(INDIRECT("FCF_PROJECTION!C8")/(1+$A15)^2)+(INDIRECT("FCF_PROJECTION!D8")/(1+$A15)^3)+(INDIRECT("FCF_PROJECTION!E8")/(1+$A15)^4)+(INDIRECT("FCF_PROJECTION!F8")/(1+$A15)^5)+((INDIRECT("FCF_PROJECTION!F8")*(1+F$7)/($A15-F$7))/(1+$A15)^5) -> 296696.72 | G15: =(INDIRECT("FCF_PROJECTION!B8")/(1+$A15)^1)+(INDIRECT("FCF_PROJECTION!C8")/(1+$A15)^2)+(INDIRECT("FCF_PROJECTION!D8")/(1+$A15)^3)+(INDIRECT("FCF_PROJECTION!E8")/(1+$A15)^4)+(INDIRECT("FCF_PROJECTION!F8")/(1+$A15)^5)+((INDIRECT("FCF_PROJECTION!F8")*(1+G$7)/($A15-G$7))/(1+$A15)^5) -> 314306.56 | H15: =(INDIRECT("FCF_PROJECTION!B8")/(1+$A15)^1)+(INDIRECT("FCF_PROJECTION!C8")/(1+$A15)^2)+(INDIRECT("FCF_PROJECTION!D8")/(1+$A15)^3)+(INDIRECT("FCF_PROJECTION!E8")/(1+$A15)^4)+(INDIRECT("FCF_PROJECTION!F8")/(1+$A15)^5)+((INDIRECT("FCF_PROJECTION!F8")*(1+H$7)/($A15-H$7))/(1+$A15)^5) -> 334625.61
A16: 0.115 | B16: =(INDIRECT("FCF_PROJECTION!B8")/(1+$A16)^1)+(INDIRECT("FCF_PROJECTION!C8")/(1+$A16)^2)+(INDIRECT("FCF_PROJECTION!D8")/(1+$A16)^3)+(INDIRECT("FCF_PROJECTION!E8")/(1+$A16)^4)+(INDIRECT("FCF_PROJECTION!F8")/(1+$A16)^5)+((INDIRECT("FCF_PROJECTION!F8")*(1+B$7)/($A16-B$7))/(1+$A16)^5) -> 231170.71 | C16: =(INDIRECT("FCF_PROJECTION!B8")/(1+$A16)^1)+(INDIRECT("FCF_PROJECTION!C8")/(1+$A16)^2)+(INDIRECT("FCF_PROJECTION!D8")/(1+$A16)^3)+(INDIRECT("FCF_PROJECTION!E8")/(1+$A16)^4)+(INDIRECT("FCF_PROJECTION!F8")/(1+$A16)^5)+((INDIRECT("FCF_PROJECTION!F8")*(1+C$7)/($A16-C$7))/(1+$A16)^5) -> 240729.08 | D16: =(INDIRECT("FCF_PROJECTION!B8")/(1+$A16)^1)+(INDIRECT("FCF_PROJECTION!C8")/(1+$A16)^2)+(INDIRECT("FCF_PROJECTION!D8")/(1+$A16)^3)+(INDIRECT("FCF_PROJECTION!E8")/(1+$A16)^4)+(INDIRECT("FCF_PROJECTION!F8")/(1+$A16)^5)+((INDIRECT("FCF_PROJECTION!F8")*(1+D$7)/($A16-D$7))/(1+$A16)^5) -> 251349.48 | E16: =(INDIRECT("FCF_PROJECTION!B8")/(1+$A16)^1)+(INDIRECT("FCF_PROJECTION!C8")/(1+$A16)^2)+(INDIRECT("FCF_PROJECTION!D8")/(1+$A16)^3)+(INDIRECT("FCF_PROJECTION!E8")/(1+$A16)^4)+(INDIRECT("FCF_PROJECTION!F8")/(1+$A16)^5)+((INDIRECT("FCF_PROJECTION!F8")*(1+E$7)/($A16-E$7))/(1+$A16)^5) -> 263219.35 | F16: =(INDIRECT("FCF_PROJECTION!B8")/(1+$A16)^1)+(INDIRECT("FCF_PROJECTION!C8")/(1+$A16)^2)+(INDIRECT("FCF_PROJECTION!D8")/(1+$A16)^3)+(INDIRECT("FCF_PROJECTION!E8")/(1+$A16)^4)+(INDIRECT("FCF_PROJECTION!F8")/(1+$A16)^5)+((INDIRECT("FCF_PROJECTION!F8")*(1+F$7)/($A16-F$7))/(1+$A16)^5) -> 276572.95 | G16: =(INDIRECT("FCF_PROJECTION!B8")/(1+$A16)^1)+(INDIRECT("FCF_PROJECTION!C8")/(1+$A16)^2)+(INDIRECT("FCF_PROJECTION!D8")/(1+$A16)^3)+(INDIRECT("FCF_PROJECTION!E8")/(1+$A16)^4)+(INDIRECT("FCF_PROJECTION!F8")/(1+$A16)^5)+((INDIRECT("FCF_PROJECTION!F8")*(1+G$7)/($A16-G$7))/(1+$A16)^5) -> 291707.02 | H16: =(INDIRECT("FCF_PROJECTION!B8")/(1+$A16)^1)+(INDIRECT("FCF_PROJECTION!C8")/(1+$A16)^2)+(INDIRECT("FCF_PROJECTION!D8")/(1+$A16)^3)+(INDIRECT("FCF_PROJECTION!E8")/(1+$A16)^4)+(INDIRECT("FCF_PROJECTION!F8")/(1+$A16)^5)+((INDIRECT("FCF_PROJECTION!F8")*(1+H$7)/($A16-H$7))/(1+$A16)^5) -> 309003.11
A19: TABLE 2: Equity Value Sensitivity
A20: Year 1 Revenue Growth vs Year 1 FCF Margin (USD Millions)
A21: Growth / Margin | B21: 0.065 | C21: 0.075 | D21: 0.085 | E21: 0.095 | F21: 0.105 | G21: 0.115 | H21: 0.125
A22: 0.08 | B22: =((FCF_PROJECTION!$B$6*(1+$A22)*B$21)/(ASSUMPTIONS!$B$19-ASSUMPTIONS!$B$21))-ASSUMPTIONS!$B$29 -> 95348.2 | C22: =((FCF_PROJECTION!$B$6*(1+$A22)*C$21)/(ASSUMPTIONS!$B$19-ASSUMPTIONS!$B$21))-ASSUMPTIONS!$B$29 -> 114940.23 | D22: =((FCF_PROJECTION!$B$6*(1+$A22)*D$21)/(ASSUMPTIONS!$B$19-ASSUMPTIONS!$B$21))-ASSUMPTIONS!$B$29 -> 134532.26 | E22: =((FCF_PROJECTION!$B$6*(1+$A22)*E$21)/(ASSUMPTIONS!$B$19-ASSUMPTIONS!$B$21))-ASSUMPTIONS!$B$29 -> 154124.29 | F22: =((FCF_PROJECTION!$B$6*(1+$A22)*F$21)/(ASSUMPTIONS!$B$19-ASSUMPTIONS!$B$21))-ASSUMPTIONS!$B$29 -> 173716.32 | G22: =((FCF_PROJECTION!$B$6*(1+$A22)*G$21)/(ASSUMPTIONS!$B$19-ASSUMPTIONS!$B$21))-ASSUMPTIONS!$B$29 -> 193308.35 | H22: =((FCF_PROJECTION!$B$6*(1+$A22)*H$21)/(ASSUMPTIONS!$B$19-ASSUMPTIONS!$B$21))-ASSUMPTIONS!$B$29 -> 212900.38
A23: 0.09 | B23: =((FCF_PROJECTION!$B$6*(1+$A23)*B$21)/(ASSUMPTIONS!$B$19-ASSUMPTIONS!$B$21))-ASSUMPTIONS!$B$29 -> 96527.35 | C23: =((FCF_PROJECTION!$B$6*(1+$A23)*C$21)/(ASSUMPTIONS!$B$19-ASSUMPTIONS!$B$21))-ASSUMPTIONS!$B$29 -> 116300.79 | D23: =((FCF_PROJECTION!$B$6*(1+$A23)*D$21)/(ASSUMPTIONS!$B$19-ASSUMPTIONS!$B$21))-ASSUMPTIONS!$B$29 -> 136074.23 | E23: =((FCF_PROJECTION!$B$6*(1+$A23)*E$21)/(ASSUMPTIONS!$B$19-ASSUMPTIONS!$B$21))-ASSUMPTIONS!$B$29 -> 155847.67 | F23: =((FCF_PROJECTION!$B$6*(1+$A23)*F$21)/(ASSUMPTIONS!$B$19-ASSUMPTIONS!$B$21))-ASSUMPTIONS!$B$29 -> 175621.1 | G23: =((FCF_PROJECTION!$B$6*(1+$A23)*G$21)/(ASSUMPTIONS!$B$19-ASSUMPTIONS!$B$21))-ASSUMPTIONS!$B$29 -> 195394.54 | H23: =((FCF_PROJECTION!$B$6*(1+$A23)*H$21)/(ASSUMPTIONS!$B$19-ASSUMPTIONS!$B$21))-ASSUMPTIONS!$B$29 -> 215167.98
A24: 0.1 | B24: =((FCF_PROJECTION!$B$6*(1+$A24)*B$21)/(ASSUMPTIONS!$B$19-ASSUMPTIONS!$B$21))-ASSUMPTIONS!$B$29 -> 97706.5 | C24: =((FCF_PROJECTION!$B$6*(1+$A24)*C$21)/(ASSUMPTIONS!$B$19-ASSUMPTIONS!$B$21))-ASSUMPTIONS!$B$29 -> 117661.35 | D24: =((FCF_PROJECTION!$B$6*(1+$A24)*D$21)/(ASSUMPTIONS!$B$19-ASSUMPTIONS!$B$21))-ASSUMPTIONS!$B$29 -> 137616.19 | E24: =((FCF_PROJECTION!$B$6*(1+$A24)*E$21)/(ASSUMPTIONS!$B$19-ASSUMPTIONS!$B$21))-ASSUMPTIONS!$B$29 -> 157571.04 | F24: =((FCF_PROJECTION!$B$6*(1+$A24)*F$21)/(ASSUMPTIONS!$B$19-ASSUMPTIONS!$B$21))-ASSUMPTIONS!$B$29 -> 177525.88 | G24: =((FCF_PROJECTION!$B$6*(1+$A24)*G$21)/(ASSUMPTIONS!$B$19-ASSUMPTIONS!$B$21))-ASSUMPTIONS!$B$29 -> 197480.73 | H24: =((FCF_PROJECTION!$B$6*(1+$A24)*H$21)/(ASSUMPTIONS!$B$19-ASSUMPTIONS!$B$21))-ASSUMPTIONS!$B$29 -> 217435.58
A25: 0.11 | B25: =((FCF_PROJECTION!$B$6*(1+$A25)*B$21)/(ASSUMPTIONS!$B$19-ASSUMPTIONS!$B$21))-ASSUMPTIONS!$B$29 -> 98885.65 | C25: =((FCF_PROJECTION!$B$6*(1+$A25)*C$21)/(ASSUMPTIONS!$B$19-ASSUMPTIONS!$B$21))-ASSUMPTIONS!$B$29 -> 119021.9 | D25: =((FCF_PROJECTION!$B$6*(1+$A25)*D$21)/(ASSUMPTIONS!$B$19-ASSUMPTIONS!$B$21))-ASSUMPTIONS!$B$29 -> 139158.16 | E25: =((FCF_PROJECTION!$B$6*(1+$A25)*E$21)/(ASSUMPTIONS!$B$19-ASSUMPTIONS!$B$21))-ASSUMPTIONS!$B$29 -> 159294.41 | F25: =((FCF_PROJECTION!$B$6*(1+$A25)*F$21)/(ASSUMPTIONS!$B$19-ASSUMPTIONS!$B$21))-ASSUMPTIONS!$B$29 -> 179430.67 | G25: =((FCF_PROJECTION!$B$6*(1+$A25)*G$21)/(ASSUMPTIONS!$B$19-ASSUMPTIONS!$B$21))-ASSUMPTIONS!$B$29 -> 199566.92 | H25: =((FCF_PROJECTION!$B$6*(1+$A25)*H$21)/(ASSUMPTIONS!$B$19-ASSUMPTIONS!$B$21))-ASSUMPTIONS!$B$29 -> 219703.17
A26: 0.12 | B26: =((FCF_PROJECTION!$B$6*(1+$A26)*B$21)/(ASSUMPTIONS!$B$19-ASSUMPTIONS!$B$21))-ASSUMPTIONS!$B$29 -> 100064.8 | C26: =((FCF_PROJECTION!$B$6*(1+$A26)*C$21)/(ASSUMPTIONS!$B$19-ASSUMPTIONS!$B$21))-ASSUMPTIONS!$B$29 -> 120382.46 | D26: =((FCF_PROJECTION!$B$6*(1+$A26)*D$21)/(ASSUMPTIONS!$B$19-ASSUMPTIONS!$B$21))-ASSUMPTIONS!$B$29 -> 140700.12 | E26: =((FCF_PROJECTION!$B$6*(1+$A26)*E$21)/(ASSUMPTIONS!$B$19-ASSUMPTIONS!$B$21))-ASSUMPTIONS!$B$29 -> 161017.78 | F26: =((FCF_PROJECTION!$B$6*(1+$A26)*F$21)/(ASSUMPTIONS!$B$19-ASSUMPTIONS!$B$21))-ASSUMPTIONS!$B$29 -> 181335.45 | G26: =((FCF_PROJECTION!$B$6*(1+$A26)*G$21)/(ASSUMPTIONS!$B$19-ASSUMPTIONS!$B$21))-ASSUMPTIONS!$B$29 -> 201653.11 | H26: =((FCF_PROJECTION!$B$6*(1+$A26)*H$21)/(ASSUMPTIONS!$B$19-ASSUMPTIONS!$B$21))-ASSUMPTIONS!$B$29 -> 221970.77
A27: 0.13 | B27: =((FCF_PROJECTION!$B$6*(1+$A27)*B$21)/(ASSUMPTIONS!$B$19-ASSUMPTIONS!$B$21))-ASSUMPTIONS!$B$29 -> 101243.95 | C27: =((FCF_PROJECTION!$B$6*(1+$A27)*C$21)/(ASSUMPTIONS!$B$19-ASSUMPTIONS!$B$21))-ASSUMPTIONS!$B$29 -> 121743.02 | D27: =((FCF_PROJECTION!$B$6*(1+$A27)*D$21)/(ASSUMPTIONS!$B$19-ASSUMPTIONS!$B$21))-ASSUMPTIONS!$B$29 -> 142242.09 | E27: =((FCF_PROJECTION!$B$6*(1+$A27)*E$21)/(ASSUMPTIONS!$B$19-ASSUMPTIONS!$B$21))-ASSUMPTIONS!$B$29 -> 162741.16 | F27: =((FCF_PROJECTION!$B$6*(1+$A27)*F$21)/(ASSUMPTIONS!$B$19-ASSUMPTIONS!$B$21))-ASSUMPTIONS!$B$29 -> 183240.23 | G27: =((FCF_PROJECTION!$B$6*(1+$A27)*G$21)/(ASSUMPTIONS!$B$19-ASSUMPTIONS!$B$21))-ASSUMPTIONS!$B$29 -> 203739.3 | H27: =((FCF_PROJECTION!$B$6*(1+$A27)*H$21)/(ASSUMPTIONS!$B$19-ASSUMPTIONS!$B$21))-ASSUMPTIONS!$B$29 -> 224238.37
A28: 0.14 | B28: =((FCF_PROJECTION!$B$6*(1+$A28)*B$21)/(ASSUMPTIONS!$B$19-ASSUMPTIONS!$B$21))-ASSUMPTIONS!$B$29 -> 102423.1 | C28: =((FCF_PROJECTION!$B$6*(1+$A28)*C$21)/(ASSUMPTIONS!$B$19-ASSUMPTIONS!$B$21))-ASSUMPTIONS!$B$29 -> 123103.58 | D28: =((FCF_PROJECTION!$B$6*(1+$A28)*D$21)/(ASSUMPTIONS!$B$19-ASSUMPTIONS!$B$21))-ASSUMPTIONS!$B$29 -> 143784.05 | E28: =((FCF_PROJECTION!$B$6*(1+$A28)*E$21)/(ASSUMPTIONS!$B$19-ASSUMPTIONS!$B$21))-ASSUMPTIONS!$B$29 -> 164464.53 | F28: =((FCF_PROJECTION!$B$6*(1+$A28)*F$21)/(ASSUMPTIONS!$B$19-ASSUMPTIONS!$B$21))-ASSUMPTIONS!$B$29 -> 185145.01 | G28: =((FCF_PROJECTION!$B$6*(1+$A28)*G$21)/(ASSUMPTIONS!$B$19-ASSUMPTIONS!$B$21))-ASSUMPTIONS!$B$29 -> 205825.48 | H28: =((FCF_PROJECTION!$B$6*(1+$A28)*H$21)/(ASSUMPTIONS!$B$19-ASSUMPTIONS!$B$21))-ASSUMPTIONS!$B$29 -> 226505.96
A29: 0.15 | B29: =((FCF_PROJECTION!$B$6*(1+$A29)*B$21)/(ASSUMPTIONS!$B$19-ASSUMPTIONS!$B$21))-ASSUMPTIONS!$B$29 -> 103602.25 | C29: =((FCF_PROJECTION!$B$6*(1+$A29)*C$21)/(ASSUMPTIONS!$B$19-ASSUMPTIONS!$B$21))-ASSUMPTIONS!$B$29 -> 124464.13 | D29: =((FCF_PROJECTION!$B$6*(1+$A29)*D$21)/(ASSUMPTIONS!$B$19-ASSUMPTIONS!$B$21))-ASSUMPTIONS!$B$29 -> 145326.02 | E29: =((FCF_PROJECTION!$B$6*(1+$A29)*E$21)/(ASSUMPTIONS!$B$19-ASSUMPTIONS!$B$21))-ASSUMPTIONS!$B$29 -> 166187.9 | F29: =((FCF_PROJECTION!$B$6*(1+$A29)*F$21)/(ASSUMPTIONS!$B$19-ASSUMPTIONS!$B$21))-ASSUMPTIONS!$B$29 -> 187049.79 | G29: =((FCF_PROJECTION!$B$6*(1+$A29)*G$21)/(ASSUMPTIONS!$B$19-ASSUMPTIONS!$B$21))-ASSUMPTIONS!$B$29 -> 207911.67 | H29: =((FCF_PROJECTION!$B$6*(1+$A29)*H$21)/(ASSUMPTIONS!$B$19-ASSUMPTIONS!$B$21))-ASSUMPTIONS!$B$29 -> 228773.56
A30: 0.16 | B30: =((FCF_PROJECTION!$B$6*(1+$A30)*B$21)/(ASSUMPTIONS!$B$19-ASSUMPTIONS!$B$21))-ASSUMPTIONS!$B$29 -> 104781.4 | C30: =((FCF_PROJECTION!$B$6*(1+$A30)*C$21)/(ASSUMPTIONS!$B$19-ASSUMPTIONS!$B$21))-ASSUMPTIONS!$B$29 -> 125824.69 | D30: =((FCF_PROJECTION!$B$6*(1+$A30)*D$21)/(ASSUMPTIONS!$B$19-ASSUMPTIONS!$B$21))-ASSUMPTIONS!$B$29 -> 146867.98 | E30: =((FCF_PROJECTION!$B$6*(1+$A30)*E$21)/(ASSUMPTIONS!$B$19-ASSUMPTIONS!$B$21))-ASSUMPTIONS!$B$29 -> 167911.28 | F30: =((FCF_PROJECTION!$B$6*(1+$A30)*F$21)/(ASSUMPTIONS!$B$19-ASSUMPTIONS!$B$21))-ASSUMPTIONS!$B$29 -> 188954.57 | G30: =((FCF_PROJECTION!$B$6*(1+$A30)*G$21)/(ASSUMPTIONS!$B$19-ASSUMPTIONS!$B$21))-ASSUMPTIONS!$B$29 -> 209997.86 | H30: =((FCF_PROJECTION!$B$6*(1+$A30)*H$21)/(ASSUMPTIONS!$B$19-ASSUMPTIONS!$B$21))-ASSUMPTIONS!$B$29 -> 231041.15
A33: Note: Table 2 uses simplified single-stage perpetuity model for directional sensitivity. Full 5-year DCF in FCF_PROJECTION sheet.
